[
  {
    "id": 639644,
    "title": "Classic Vanilla-Orange Sugar Cookies",
    "sourceName": "Foodista",
    "image": "https://spoonacular.com/recipeImages/639644-556x370.jpg",
    "timestamp": 1682431322509
  },
  {
    "id": 41318,
    "title": "Savory Carrot Bread",
    "image": "https://spoonacular.com/recipeImages/41318-312x231.jpg",
    "timestamp": 1682633246200
  },
  {
    "id": 1087818,
    "title": "Smoky spiced Jollof rice & coconut-fried plantain",
    "image": "https://spoonacular.com/recipeImages/1087818-312x231.jpg",
    "timestamp": 1682633438680
  },
  {
    "id": 481777,
    "title": "Whole Roasted Harissa Chicken",
    "sourceName": "Feasting at Home",
    "image": "https://spoonacular.com/recipeImages/481777-556x370.jpg",
    "timestamp": 1682633782909
  },
  {
    "id": 701811,
    "title": "Chocolate and hazelnut cake (Torta gianduia)",
    "sourceName": "bbc.co.uk",
    "image": "https://spoonacular.com/recipeImages/701811-556x370.jpg",
    "timestamp": 1682636132437
  },
  {
    "id": 665257,
    "title": "Whole Grain Pumpkin Bread",
    "sourceName": "foodista.com",
    "image": "https://spoonacular.com/recipeImages/665257-556x370.jpg",
    "timestamp": 1682636322272
  }
]
